Workbook

Sheet Cover
B12: COMMERCIAL PROPOSAL
B13: (Financial Proposal — Lot A & Lot B)
B15: Pakistan Saudi Business Forum
B16: & Pakistan Pavilion at LEAP 2026
B17: Riyadh, Kingdom of Saudi Arabia · 30 August – 3 September 2026
B21: PREPARED FOR
B22: Pakistan Software Export Board (PSEB)
B23: Ministry of IT & Telecommunication, Government of Pakistan
B24: 6th Floor, New State Life Tower, Jinnah Avenue, Blue Area, Islamabad
B26: In response to PSEB RFQ — Onboarding an Event Management Vendor for the Pakistan Saudi Business Forum and the Pakistan Pavilion at LEAP 2026 in Riyadh, Kingdom of Saudi Arabia
B29: PREPARED BY
B30: Miradore Experiences — Riyadh, Kingdom of Saudi Arabia
B32: Ref: MIR-PSEB-LEAP-2026-001 Date: 21 July 2026 Validity: 60 days
A35: End-to-End Event Management · Turnkey Pavilion Construction · Premium Branding & AV · Media Production

Sheet Summary
A1: EXECUTIVE SUMMARY & COMMERCIAL OVERVIEW
A2: Pakistan Saudi Business Forum (Lot A) · Pakistan Pavilion at LEAP 2026 (Lot B) · Riyadh, KSA
B4: Miradore Experiences is pleased to submit this financial proposal for both lots of the PSEB RFQ. Lot A covers the 300-guest Pakistan Saudi Business Forum at Crowne Plaza Riyadh RDC — the hotel venue & catering package is passed through at actual cost, with all production, branding, AV, staging and media services itemized at unit rates. Lot B covers the 162-SQM Pakistan Pavilion at Riyadh Exhibition & Convention Centre, Malham (Hall 3 — H170 / J170), offered as a single all-inclusive turnkey package (design, fabrication, approvals, power and installation) plus daily hospitality, provisioning, cleaning and multi-crew media coverage across all four LEAP days.
B6: COMMERCIAL PARAMETERS (editable inputs)
B7: VAT (Kingdom of Saudi Arabia) | C7: 0.15 | D7: Applied on all services
B8: Agency Commission / Management Fee | C8: 0.12 | D8: Applied on each lot subtotal
B9: Exchange rate — PKR per 1 SAR (reference) | C9: 75.5 | D9: Update on submission date; drives all PKR equivalents
B11: COMMERCIAL SUMMARY
B12: Description | C12: Amount (SAR) | D12: Amount (PKR) | E12: Notes
B13: Lot A — Pakistan Saudi Business Forum (30 Aug 2026) | C13: ='Lot A - Forum'!F20 -> 510000 | D13: =ROUND(C13*Summary!$C$9,0) -> 38505000 | E13: Incl. Crowne Plaza venue & catering package at cost (325,000) + itemized production & services
B14: Lot B — Pakistan Pavilion at LEAP 2026 (31 Aug – 3 Sep) | C14: ='Lot B - Pavilion'!F11 -> 317680 | D14: =ROUND(C14*Summary!$C$9,0) -> 23984840 | E14: Turnkey pavilion package + LEAP-days services — see Lot B sheet
B15: Combined Subtotal | C15: =C13+C14 -> 827680 | D15: =ROUND(C15*Summary!$C$9,0) -> 62489840
B16: Agency Commission / Management Fee | C16: ='Lot A - Forum'!F21+'Lot B - Pavilion'!F12 -> 99321.6 | D16: =ROUND(C16*Summary!$C$9,0) -> 7498781 | E16: As per Commercial Parameters
B17: Total (excl. VAT) | C17: =C15+C16 -> 927001.6 | D17: =ROUND(C17*Summary!$C$9,0) -> 69988621
B18: VAT | C18: =ROUND(C17*Summary!$C$7,2) -> 139050.24 | D18: =ROUND(C18*Summary!$C$9,0) -> 10498293
B19: GRAND TOTAL — BOTH LOTS (incl. VAT) | C19: =C17+C18 -> 1066051.8 | D19: =ROUND(C19*Summary!$C$9,0) -> 80486914 | E19: Inclusive of all applicable taxes
B21: LOT-WISE TOTALS (each lot priced to stand alone for independent award)
B22: Lot | C22: Total excl. VAT (SAR) | D22: Total incl. VAT (SAR) | E22: Total incl. VAT (PKR)
B23: Lot A — Business Forum (incl. agency commission) | C23: ='Lot A - Forum'!F22 -> 571200 | D23: ='Lot A - Forum'!F24 -> 656880 | E23: =ROUND(D23*Summary!$C$9,0) -> 49594440
B24: Lot B — LEAP Pavilion (incl. agency commission) | C24: ='Lot B - Pavilion'!F13 -> 355801.6 | D24: ='Lot B - Pavilion'!F15 -> 409171.84 | E24: =ROUND(D24*Summary!$C$9,0) -> 30892474
B26: PAYMENT TERMS & KEY CONDITIONS
B27: • Preferred Payment Terms (negotiable): 50% advance upon confirmation / work order — primarily to cover the mandatory advance payment required by Crowne Plaza Riyadh RDC to secure the venue, plus mobilization of fabrication and long-lead items; 30% two (2) days before the event; 20% balance after the event, upon successful delivery and verification.
B28: • The Crowne Plaza Riyadh RDC venue & catering package (Lot A, item A.1) is passed through at actual hotel package cost, with no markup.
B29: • Prices are quoted in Saudi Riyals (SAR); PKR equivalents are provided at the reference exchange rate stated above and will be aligned to the prevailing rate at invoicing.
B30: • Quoted totals are inclusive of all applicable taxes; VAT (15%) is shown separately for full transparency.
B31: • PSEB may increase or decrease quantities of any item; unit rates above will apply pro-rata.
B32: • All content, creative assets and campaign data produced under either lot remain the exclusive intellectual property of PSEB; no material will be disclosed or published without PSEB's prior written approval.
B33: • A dedicated Project Manager is assigned exclusively to PSEB as single point of contact (see Team & Resource Plan).
B34: • Menu options for the 5-course continental buffet will be provided for PSEB approval upon award.
B35: • Validity: 60 days from the date of submission.

Sheet Lot A - Forum
A1: LOT A — PAKISTAN SAUDI BUSINESS FORUM
A2: Crowne Plaza Riyadh RDC · 30 August 2026 · 300 Guests · Itemized BOQ (SAR, with PKR equivalents)
A4: Item Code | B4: Description of Sourced Scope | C4: Qty | D4: Unit | E4: Unit Rate (SAR) | F4: Total (SAR) | G4: Unit Rate (PKR) | H4: Total (PKR)
A5: A.1 | B5: Venue Booking for 30 Aug 2026 — Crowne Plaza Riyadh RDC Hotel: booking on PSEB's behalf and securing the venue by facilitating all mandatory advance payments required by hotel management. All-inclusive hotel package covering ballroom/hall space for 300 guests, 5-course continental buffet dinner with two coffee-break services, banquet seating & tables, hotel service staff and dedicated 5 Mbps internet. Passed through at actual hotel package cost. | C5: 1 | D5: Package | E5: 325000 | F5: =ROUND(C5*E5,2) -> 325000 | G5: =ROUND(E5*Summary!$C$9,0) -> 24537500 | H5: =ROUND(F5*Summary!$C$9,0) -> 24537500
A6: A.1.1 | B6: Event Management, Production Planning, Venue Coordination & Technical Rehearsal — end-to-end show management for the Forum. | C6: 1 | D6: Job | E6: 18500 | F6: =ROUND(C6*E6,2) -> 18500 | G6: =ROUND(E6*Summary!$C$9,0) -> 1396750 | H6: =ROUND(F6*Summary!$C$9,0) -> 1396750
A7: A.1.2 | B7: Main Stage — portable stage 10m x 4m (40 sqm) with premium stage carpet and step access, as part of the main-stage arrangements under A.1. | C7: 1 | D7: Job | E7: 12500 | F7: =ROUND(C7*E7,2) -> 12500 | G7: =ROUND(E7*Summary!$C$9,0) -> 943750 | H7: =ROUND(F7*Summary!$C$9,0) -> 943750
A8: A.2 | B8: VVIP Front-Row Premium Sofa Seating Layout with personalised name tags — 50 premium sofas, including 25 coffee tables with black stretch cloth and floral table-top arrangements. | C8: 1 | D8: Lot | E8: 19500 | F8: =ROUND(C8*E8,2) -> 19500 | G8: =ROUND(E8*Summary!$C$9,0) -> 1472250 | H8: =ROUND(F8*Summary!$C$9,0) -> 1472250
A9: A.3 | B9: 10ft x 8ft Media Wall (flex with stand) outside the conference hall, with red carpet (12m x 2m), ambiance lighting and 6 Q-poles for entrance styling. | C9: 1 | D9: Job | E9: 10500 | F9: =ROUND(C9*E9,2) -> 10500 | G9: =ROUND(E9*Summary!$C$9,0) -> 792750 | H9: =ROUND(F9*Summary!$C$9,0) -> 792750
A10: A.4 | B10: Reception / Guest Registration Desk with 2 chairs and flex backdrop branding. | C10: 1 | D10: Job | E10: 13500 | F10: =ROUND(C10*E10,2) -> 13500 | G10: =ROUND(E10*Summary!$C$9,0) -> 1019250 | H10: =ROUND(F10*Summary!$C$9,0) -> 1019250
A11: A.5 | B11: High-Luminance 55" Digital Standees around the greeting zone, including electricity sourcing and PSEB-approved digital content loop (content prepared by vendor). | C11: 4 | D11: Nos | E11: 1350 | F11: =ROUND(C11*E11,2) -> 5400 | G11: =ROUND(E11*Summary!$C$9,0) -> 101925 | H11: =ROUND(F11*Summary!$C$9,0) -> 407700
A12: A.6 | B12: Complete Lighting & Sound System for keynotes, presentations and panel discussions — line-array speakers, digital console, wireless and podium microphones, moving heads, parcans, city colors and uplights, with dedicated audio and lighting engineers. | C12: 1 | D12: Job | E12: 26500 | F12: =ROUND(C12*E12,2) -> 26500 | G12: =ROUND(E12*Summary!$C$9,0) -> 2000750 | H12: =ROUND(F12*Summary!$C$9,0) -> 2000750
A13: A.7 | B13: High-Resolution 30ft x 12ft SMD Main Screen with integrated neon border, including media server, washout and full content design as per PSEB-approved event flow and speakers. | C13: 1 | D13: Job | E13: 34500 | F13: =ROUND(C13*E13,2) -> 34500 | G13: =ROUND(E13*Summary!$C$9,0) -> 2604750 | H13: =ROUND(F13*Summary!$C$9,0) -> 2604750
A14: A.7.1 | B14: 6ft x 8ft SMD Mirror Panels throughout the hall, with content designed as per PSEB's directions and approval. | C14: 4 | D14: Nos | E14: 3150 | F14: =ROUND(C14*E14,2) -> 12600 | G14: =ROUND(E14*Summary!$C$9,0) -> 237825 | H14: =ROUND(F14*Summary!$C$9,0) -> 951300
A15: A.8 | B15: Customised wooden speaker podium with the official event logo integrated onto the front fascia, podium microphone and step stool. | C15: 1 | D15: Job | E15: 5000 | F15: =ROUND(C15*E15,2) -> 5000 | G15: =ROUND(E15*Summary!$C$9,0) -> 377500 | H15: =ROUND(F15*Summary!$C$9,0) -> 377500
A16: A.9 | B16: 5-Course Continental Buffet Dinner for 300 participants (buffet setup) with table service for the Minister and VVIP tables — included within the Crowne Plaza hotel package under A.1; menu options to be provided for PSEB approval. | C16: — | D16: — | F16: Included in A.1 | G16: — | H16: —
A17: A.10 | B17: Dedicated on-site project coordinator liaising continuously with hotel banquet staff to ensure flawless event flow throughout the Forum. | C17: 1 | D17: Job | E17: 5500 | F17: =ROUND(C17*E17,2) -> 5500 | G17: =ROUND(E17*Summary!$C$9,0) -> 415250 | H17: =ROUND(F17*Summary!$C$9,0) -> 415250
A18: A.11 | B18: Sourced Media Crew — one professional photography team and one videography team for complete event coverage, including: 100% raw photo/video upload to a shared secure Google Drive by midnight; polished 90-second highlight reel next day; ten short speaker/segment clips (15-sec and 30-sec variants) for social media next day; and a 3–5 minute high-production event documentary within 2 days of the Forum. | C18: 1 | D18: Job | E18: 11500 | F18: =ROUND(C18*E18,2) -> 11500 | G18: =ROUND(E18*Summary!$C$9,0) -> 868250 | H18: =ROUND(F18*Summary!$C$9,0) -> 868250
A19: A.12 | B19: Professional Ushers / Hostesses for guest management, registration support and VVIP handling. | C19: 10 | D19: Person | E19: 950 | F19: =ROUND(C19*E19,2) -> 9500 | G19: =ROUND(E19*Summary!$C$9,0) -> 71725 | H19: =ROUND(F19*Summary!$C$9,0) -> 717250
A20: Subtotal | F20: =SUM(F5:F19) -> 510000 | H20: =ROUND(F20*Summary!$C$9,0) -> 38505000
A21: Agency Commission / Management Fee (12%) | F21: =ROUND(F20*Summary!$C$8,2) -> 61200 | H21: =ROUND(F21*Summary!$C$9,0) -> 4620600
A22: Total (excl. VAT) | F22: =F20+F21 -> 571200 | H22: =ROUND(F22*Summary!$C$9,0) -> 43125600
A23: VAT (15%) | F23: =ROUND(F22*Summary!$C$7,2) -> 85680 | H23: =ROUND(F23*Summary!$C$9,0) -> 6468840
A24: LOT A — TOTAL (incl. VAT) | F24: =F22+F23 -> 656880 | H24: =ROUND(F24*Summary!$C$9,0) -> 49594440
A27: Note 1: A.1 is the Crowne Plaza Riyadh RDC all-inclusive package (hall space + full catering for 300 guests) passed through at actual hotel package cost, with no markup.
A28: Note 2: A.9 (5-course continental buffet & coffee breaks) is included within the A.1 hotel package; final headcount will be settled on actuals as per PSEB confirmation.
A29: Note 3: All artwork and screen content will be produced by Miradore and released only after PSEB's written approval.

Sheet Lot B - Pavilion
A1: LOT B — PAKISTAN PAVILION AT LEAP 2026
A2: Riyadh Exhibition & Convention Centre (RECC), Malham · 31 Aug – 3 Sep 2026 · 162 SQM · Hall 3 (H170 / J170)
A4: Item Code | B4: Description of Sourced Scope | C4: Qty | D4: Unit | E4: Unit Rate (SAR) | F4: Total (SAR) | G4: Unit Rate (PKR) | H4: Total (PKR)
A5: B.1 – B.6 | B5: TURNKEY PAKISTAN PAVILION — ALL-INCLUSIVE PACKAGE (162 SQM · 3 Blocks · 20 Exhibitor Booths · 30-SQM Networking Lounge · Ministerial Meeting Room), built to Annex I–III blueprints & specifications. Package includes: • Design, fabrication, sourcing, logistics & transportation to RECC Malham; structural build of Blocks A, B & C; on-site management and full dismantling • Block A & C wood/MDF build (16 booths: 2 x 9-SQM + 6 x 6-SQM per block); Block B premium architectural build (4 x 6-SQM booths, lounge & meeting room) • Glass-walled ministerial meeting room (two 250cm x 240cm glass walls + glass door) with 55" LED TV, 2 single-seater and one 2-seater sofa • P2.6 LED screens (3.5m x 1m) for block branding; 43" LED TV per booth; backlit light boxes; neon accent lighting; premium wooden flooring with neon edge • 3D acrylic + neon block logos, die-cut vinyl logos and full booth branding • Branded info counter with bar stool, 3 chairs and 1 round table per booth; networking lounge seating with round tables • Organizer stand-build permit, official stand audit approval, structural clearance and health/safety/security clearances ahead of move-in deadlines • Main electrical power line drops, panel deployment and per-booth hookups — minimum 2 multi-pin power sockets in every booth, meeting room and networking area, engineered to run all SMDs, LCDs and lighting rigs | C5: 1 | D5: Package | E5: 232000 | F5: =ROUND(C5*E5,2) -> 232000 | G5: =ROUND(E5*Summary!$C$9,0) -> 17516000 | H5: =ROUND(F5*Summary!$C$9,0) -> 17516000
A6: B.7 | B6: Running Tea & Coffee Station for the entire pavilion (approx. 500 cups/day) with service staff and consumables — 4 days. | C6: 4 | D6: Day | E6: 4250 | F6: =ROUND(C6*E6,2) -> 17000 | G6: =ROUND(E6*Summary!$C$9,0) -> 320875 | H6: =ROUND(F6*Summary!$C$9,0) -> 1283500
A7: B.8 | B7: Lounge Catering — premium assorted dates, traditional one-bite snacks and local confectioneries served in traditional plates daily (approx. 200 person-servings/day), with mineral water for the networking lounge — 4 days. | C7: 4 | D7: Day | E7: 4800 | F7: =ROUND(C7*E7,2) -> 19200 | G7: =ROUND(E7*Summary!$C$9,0) -> 362400 | H7: =ROUND(F7*Summary!$C$9,0) -> 1449600
A8: B.9 | B8: Daily Stall Provisions — 6 small chilled mineral water bottles delivered to every booth at the start of each morning session, plus 100 bottles/day for the lounge (approx. 880 bottles over 4 days). | C8: 880 | D8: Bottle | E8: 3.5 | F8: =ROUND(C8*E8,2) -> 3080 | G8: =ROUND(E8*Summary!$C$9,0) -> 264 | H8: =ROUND(F8*Summary!$C$9,0) -> 232540
A9: B.10 | B9: Continuous Sanitation, Waste Removal & Booth Dustbin Deployment — individual dustbin in each of the 20 booths emptied routinely, with dedicated daily cleaning of all booths and lounge area — 4 days. | C9: 4 | D9: Day | E9: 1850 | F9: =ROUND(C9*E9,2) -> 7400 | G9: =ROUND(E9*Summary!$C$9,0) -> 139675 | H9: =ROUND(F9*Summary!$C$9,0) -> 558700
A10: B.11 | B10: Sourced Media Crew — 2 dedicated photography teams and 2 videography teams, permanent full-day presence for 4 days covering ministerial bilaterals, speaker sessions, booth engagement and visitor traffic. Daily deliverables: 100% raw uploads to shared Drive by midnight; 90-second daily highlight video by next morning; minimum 10 short clips daily (15-sec / 30-sec) by 10 AM; and 3–5 minute pavilion documentary within 2 days of event close. | C10: 4 | D10: Day | E10: 9750 | F10: =ROUND(C10*E10,2) -> 39000 | G10: =ROUND(E10*Summary!$C$9,0) -> 736125 | H10: =ROUND(F10*Summary!$C$9,0) -> 2944500
A11: Subtotal | F11: =SUM(F5:F10) -> 317680 | H11: =ROUND(F11*Summary!$C$9,0) -> 23984840
A12: Agency Commission / Management Fee (12%) | F12: =ROUND(F11*Summary!$C$8,2) -> 38121.6 | H12: =ROUND(F12*Summary!$C$9,0) -> 2878181
A13: Total (excl. VAT) | F13: =F11+F12 -> 355801.6 | H13: =ROUND(F13*Summary!$C$9,0) -> 26863021
A14: VAT (15%) | F14: =ROUND(F13*Summary!$C$7,2) -> 53370.24 | H14: =ROUND(F14*Summary!$C$9,0) -> 4029453
A15: LOT B — TOTAL (incl. VAT) | F15: =F13+F14 -> 409171.84 | H15: =ROUND(F15*Summary!$C$9,0) -> 30892474
A17: Note 1: Line B.1 – B.6 consolidates the complete turnkey pavilion scope of the RFP (fabrication & logistics, Block A & C build, Block B build, organizer approvals & clearances, main power supply and per-booth electrical hookups) as one all-inclusive package price — everything required to hand over a fully operational 162-SQM pavilion before the move-in deadline.
A18: Note 2: A dedicated Project Manager and on-site coordination team (including tea servers) are deployed from project start for exhibitor coordination, booth design/artwork liaison and troubleshooting.
A19: Note 3: All raw footage, edits and creative assets are delivered as exclusive intellectual property of PSEB.

Sheet Team
A1: RESOURCE PLAN & TALENT PROFILES
A2: Dedicated delivery team — single point of contact assigned exclusively to PSEB
A4: Role | B4: Profile & Responsibility | C4: Deployment
A5: Project Director & Client Lead | B5: Overall engagement owner and commercial lead; direct escalation line for PSEB leadership; oversees both lots end-to-end. | C5: Full engagement, pre-event & on-site
A6: Dedicated Project Manager (single point of contact for PSEB) | B6: Assigned exclusively to PSEB for all pre-event and on-site liaison: exhibitor coordination, booth design & artwork approvals, schedule control, daily progress reporting and troubleshooting. | C6: Full-time from award to closeout
A7: Production Manager — Pavilion | B7: Leads fabrication, logistics and build of the 162-SQM pavilion; manages workshop, transport and RECC move-in/teardown per organizer schedule. | C7: Fabrication through teardown
A8: Site Supervisor & Safety Officer — RECC | B8: On-floor supervision of build crews; compliance with organizer stand audit, structural and HSE requirements. | C8: Move-in to teardown
A9: Certified Electrical Engineer | B9: Main power drops, panel deployment and per-booth hookups per Annex II/III load metrics; on-call through all live days. | C9: Build + 4 live days
A10: AV & Technical Lead — Forum | B10: SMD screens, mirror panels, sound and lighting systems at Crowne Plaza RDC; runs technical rehearsal and show calling. | C10: 29 – 30 Aug
A11: Content Designer / Editor (2) | B11: Screen content per PSEB-approved event flow, daily highlight videos, social snippets and final documentaries. | C11: Pre-event + daily during events
A12: Photography Teams (2) & Videography Teams (2) | B12: Independent professional crews with permanent presence: ministerial bilaterals, speaker sessions, booth engagement and visitor traffic; Forum coverage on 30 Aug. | C12: 30 Aug + 4 LEAP days
A13: Hospitality Team — Tea Servers & Lounge Attendants (4) | B13: Runs the tea/coffee station (approx. 500 cups/day), lounge dates & snacks service and daily water provisioning to all 20 booths. | C13: 4 LEAP days
A14: Cleaning Crew (4) | B14: Continuous cleaning of pavilion, booths and lounge; dustbin emptying and waste removal. | C14: 4 LEAP days
A15: On-site Event Coordinators (2) | B15: Guest registration, VVIP handling and hotel banquet liaison at the Business Forum; floor coordination at LEAP. | C15: 30 Aug + 4 LEAP days
A17: CVs and detailed profiles of the assigned Project Manager and key personnel will be shared with PSEB upon award, prior to mobilization.

Sheet Internal
A1: INTERNAL — COSTING & MARGIN (DO NOT PRINT / DO NOT SHARE)
A2: Quote cells pull live from the BOQ sheets; cost basis from supplier quotes as noted
A4: Item | B4: Line | C4: Quote (SAR) | D4: Cost (SAR) | E4: Margin (SAR) | F4: Margin % | G4: Cost source
A5: A.1 | B5: Crowne Plaza package (hall + catering) — pass-through | C5: ='Lot A - Forum'!F5 -> 325000 | D5: 325000 | E5: =C5-D5 -> 0 | F5: =IF(D5=0,"n/a",C5/D5-1) -> 0 | G5: Crowne Plaza RDC offer: 325,000 + 15% VAT, incl. hall space, dinner + 2 coffee breaks (priced as-is, no markup)
A6: A.1.1 | B6: Event management & technical rehearsal | C6: ='Lot A - Forum'!F6 -> 18500 | D6: 10000 | E6: =C6-D6 -> 8500 | F6: =IF(D6=0,"n/a",C6/D6-1) -> 0.85 | G6: Innovation BOQ A.1 10,000
A7: A.1.2 | B7: Stage 10m x 4m + carpet | C7: ='Lot A - Forum'!F7 -> 12500 | D7: 7400 | E7: =C7-D7 -> 5100 | F7: =IF(D7=0,"n/a",C7/D7-1) -> 0.68918919 | G7: Innovation BOQ A.8 5,600 + stage carpet 1,800
A8: A.2 | B8: VVIP 50 sofas + tables + florals | C8: ='Lot A - Forum'!F8 -> 19500 | D8: 12250 | E8: =C8-D8 -> 7250 | F8: =IF(D8=0,"n/a",C8/D8-1) -> 0.59183673 | G8: Innovation BOQ A.2 subtotal 12,250
A9: A.3 | B9: Media wall + red carpet + Q-poles | C9: ='Lot A - Forum'!F9 -> 10500 | D9: 6500 | E9: =C9-D9 -> 4000 | F9: =IF(D9=0,"n/a",C9/D9-1) -> 0.61538462 | G9: Innovation BOQ A.3 6,500
A10: A.4 | B10: Registration desk + backdrop | C10: ='Lot A - Forum'!F10 -> 13500 | D10: 8500 | E10: =C10-D10 -> 5000 | F10: =IF(D10=0,"n/a",C10/D10-1) -> 0.58823529 | G10: Innovation BOQ A.4 8,500
A11: A.5 | B11: Digital standees x4 | C11: ='Lot A - Forum'!F11 -> 5400 | D11: 3200 | E11: =C11-D11 -> 2200 | F11: =IF(D11=0,"n/a",C11/D11-1) -> 0.6875 | G11: Innovation BOQ A.5 4 x 800
A12: A.6 | B12: Lighting + sound complete | C12: ='Lot A - Forum'!F12 -> 26500 | D12: 15500 | E12: =C12-D12 -> 11000 | F12: =IF(D12=0,"n/a",C12/D12-1) -> 0.70967742 | G12: Innovation BOQ A.6 10,000 + A.6.1 5,500
A13: A.7 | B13: SMD main screen + server/washout | C13: ='Lot A - Forum'!F13 -> 34500 | D13: 20500 | E13: =C13-D13 -> 14000 | F13: =IF(D13=0,"n/a",C13/D13-1) -> 0.68292683 | G13: Innovation BOQ A.7 14,000 + A.7.1 6,500
A14: A.7.1 | B14: SMD mirror panels x4 | C14: ='Lot A - Forum'!F14 -> 12600 | D14: 6300 | E14: =C14-D14 -> 6300 | F14: =IF(D14=0,"n/a",C14/D14-1) -> 1 | G14: Est. ~350/sqm x 17.8 sqm + rigging (est.)
A15: A.8 | B15: Branded podium + mic + stool | C15: ='Lot A - Forum'!F15 -> 5000 | D15: 2800 | E15: =C15-D15 -> 2200 | F15: =IF(D15=0,"n/a",C15/D15-1) -> 0.78571429 | G15: Market estimate (not in supplier BOQ)
A16: A.10 | B16: On-site project coordinator | C16: ='Lot A - Forum'!F17 -> 5500 | D16: 2500 | E16: =C16-D16 -> 3000 | F16: =IF(D16=0,"n/a",C16/D16-1) -> 1.2 | G16: Internal staffing estimate
A17: A.11 | B17: Media crew + full deliverables | C17: ='Lot A - Forum'!F18 -> 11500 | D17: 6000 | E17: =C17-D17 -> 5500 | F17: =IF(D17=0,"n/a",C17/D17-1) -> 0.91666667 | G17: Innovation BOQ A.10 4,500 + editing/deliverables est. 1,500
A18: A.12 | B18: Ushers x10 | C18: ='Lot A - Forum'!F19 -> 9500 | D18: 6500 | E18: =C18-D18 -> 3000 | F18: =IF(D18=0,"n/a",C18/D18-1) -> 0.46153846 | G18: Innovation BOQ A.11 10 x 650
A19: B.1-B.6 | B19: Turnkey pavilion (booth package) | C19: ='Lot B - Pavilion'!F5 -> 232000 | D19: 130435 | E19: =C19-D19 -> 101565 | F19: =IF(D19=0,"n/a",C19/D19-1) -> 0.7786637 | G19: Alpha Dimensions revised QUT-0126-26: 130,435 + VAT = 150,000 incl. VAT (orig. detailed quote 335,810 excl. VAT)
A20: B.7 | B20: Tea & coffee station 4 days | C20: ='Lot B - Pavilion'!F6 -> 17000 | D20: 6000 | E20: =C20-D20 -> 11000 | F20: =IF(D20=0,"n/a",C20/D20-1) -> 1.8333333 | G20: Partially covered in Alpha revised (catering incl.); staff/consumables top-up est.
A21: B.8 | B21: Lounge dates & snacks 4 days | C21: ='Lot B - Pavilion'!F7 -> 19200 | D21: 10000 | E21: =C21-D21 -> 9200 | F21: =IF(D21=0,"n/a",C21/D21-1) -> 0.92 | G21: Catering supplier est. ~2,500/day
A22: B.9 | B22: Water bottles 880 | C22: ='Lot B - Pavilion'!F8 -> 3080 | D22: 1320 | E22: =C22-D22 -> 1760 | F22: =IF(D22=0,"n/a",C22/D22-1) -> 1.3333333 | G22: Est. 1.50/bottle wholesale
A23: B.10 | B23: Cleaning & waste 4 days | C23: ='Lot B - Pavilion'!F9 -> 7400 | D23: 4800 | E23: =C23-D23 -> 2600 | F23: =IF(D23=0,"n/a",C23/D23-1) -> 0.54166667 | G23: Est. 1,200/day
A24: B.11 | B24: 2+2 media crews 4 days + editing | C24: ='Lot B - Pavilion'!F10 -> 39000 | D24: 24000 | E24: =C24-D24 -> 15000 | F24: =IF(D24=0,"n/a",C24/D24-1) -> 0.625 | G24: Partially covered in Alpha revised (coverage incl.); add'l crews/editing est. 6,000/day
B25: TOTALS (excl. VAT, before agency commission) | C25: =SUM(C5:C24) -> 827680 | D25: =SUM(D5:D24) -> 609505 | E25: =C25-D25 -> 218175 | F25: =IF(D25=0,"n/a",C25/D25-1) -> 0.35795441
B26: Agency commission (12% on lot subtotals) — additional revenue on top | C26: ='Lot A - Forum'!F21+'Lot B - Pavilion'!F12 -> 99321.6
A28: Assumptions: Crowne Plaza RDC package 325,000 SAR + 15% VAT (hall + dinner + 2 coffee breaks, 300 pax) per offer relayed 18 Jul 2026, passed through at cost; supplier costs from Innovation Events BOQ (WhatsApp, 18 Jul 2026) and Alpha Dimensions QUT-0126-26 (20 Jul 2026); 'est.' items are internal estimates. Costs above are excl. VAT; input VAT on supplier invoices is recoverable.
